auger/__init__.py
auger/runtime.py
auger/tracer.py
auger/generator/__init__.py
auger/generator/default.py
auger/generator/generator.py
auger_python-0.1.35.dist-info/LICENSE
auger_python-0.1.35.dist-info/METADATA
auger_python-0.1.35.dist-info/WHEEL
auger_python-0.1.35.dist-info/top_level.txt
auger_python-0.1.35.dist-info/RECORD
