Metadata-Version: 2.1
Name: auger-python
Version: 0.1.35
Summary: Automatically generate unit tests for Python code
Home-page: https://github.com/laffra/auger
Author: Chris Laffra
Author-email: laffra@gmail.com
License: UNKNOWN
Platform: UNKNOWN
Classifier: Programming Language :: Python :: 2.7
Classifier: License :: OSI Approved :: MIT License
Classifier: Operating System :: OS Independent
Requires-Dist: funcsigs
Requires-Dist: mock
Requires-Dist: six
